{"cameraMode":{"drawMode":0,"name":"Shaded","section":"Shading Mode"},"sceneLighting":true,"audioPlay":false,"sceneViewState":{"m_AlwaysRefresh":false,"showFog":true,"showSkybox":true,"showFlares":true,"showImageEffects":true,"showParticleSystems":true,"showVisualEffectGraphs":true,"m_FxEnabled":true},"in2DMode":false,"pivot":{"x":-2.2398271560668947,"y":-3.569581985473633,"z":-4.256194114685059},"rotation":{"x":-0.012757251970469952,"y":0.9541445970535278,"z":-0.2975912094116211,"w":-0.04290904849767685},"size":10.0,"orthographic":false}